yadg/__init__.py
yadg/core.py
yadg/main.py
yadg/subcommands.py
yadg/dgutils/__init__.py
yadg/dgutils/btools.py
yadg/dgutils/dateutils.py
yadg/dgutils/dsutils.py
yadg/dgutils/helpers.py
yadg/dgutils/pintutils.py
yadg/dgutils/schemautils.py
yadg/extractors/__init__.py
yadg/extractors/agilent/__init__.py
yadg/extractors/agilent/ch.py
yadg/extractors/agilent/csv.py
yadg/extractors/agilent/dx.py
yadg/extractors/basic/__init__.py
yadg/extractors/basic/csv.py
yadg/extractors/drycal/__init__.py
yadg/extractors/drycal/common.py
yadg/extractors/drycal/csv.py
yadg/extractors/drycal/rtf.py
yadg/extractors/drycal/txt.py
yadg/extractors/eclab/__init__.py
yadg/extractors/eclab/mpr.py
yadg/extractors/eclab/mpr_columns.py
yadg/extractors/eclab/mpt.py
yadg/extractors/eclab/mpt_columns.py
yadg/extractors/eclab/techniques.py
yadg/extractors/empalc/__init__.py
yadg/extractors/empalc/csv.py
yadg/extractors/empalc/xlsx.py
yadg/extractors/example/__init__.py
yadg/extractors/ezchrom/__init__.py
yadg/extractors/ezchrom/asc.py
yadg/extractors/ezchrom/dat.py
yadg/extractors/fhimcpt/__init__.py
yadg/extractors/fhimcpt/csv.py
yadg/extractors/fhimcpt/vna.py
yadg/extractors/fusion/__init__.py
yadg/extractors/fusion/csv.py
yadg/extractors/fusion/json.py
yadg/extractors/fusion/zip.py
yadg/extractors/panalytical/__init__.py
yadg/extractors/panalytical/common.py
yadg/extractors/panalytical/csv.py
yadg/extractors/panalytical/xrdml.py
yadg/extractors/panalytical/xy.py
yadg/extractors/phi/__init__.py
yadg/extractors/phi/spe.py
yadg/extractors/picolog/__init__.py
yadg/extractors/picolog/tc08.py
yadg/extractors/quadstar/__init__.py
yadg/extractors/quadstar/sac.py
yadg/extractors/tomato/__init__.py
yadg/extractors/tomato/json.py
yadg/extractors/touchstone/__init__.py
yadg/extractors/touchstone/snp.py
yadg-6.2.2.dist-info/licenses/LICENSE
yadg-6.2.2.dist-info/METADATA
yadg-6.2.2.dist-info/WHEEL
yadg-6.2.2.dist-info/entry_points.txt
yadg-6.2.2.dist-info/top_level.txt
yadg-6.2.2.dist-info/RECORD
