Metadata-Version: 2.4
Name: yadg
Version: 6.2.2
Summary: yet another datagram
Author: Peter Kraus, Nicolas Vetsch, Carla Terboven, Graham Kimbell
Maintainer-email: Peter Kraus <peter.kraus@tu-berlin.de>
Project-URL: Documentation, https://dgbowl.github.io/yadg/main
Project-URL: Issues, https://github.com/dgbowl/yadg/issues
Project-URL: Repository, https://github.com/dgbowl/yadg/
Classifier: Development Status :: 5 - Production/Stable
Classifier: License :: OSI Approved :: GNU General Public License v3 or later (GPLv3+)
Classifier: Programming Language :: Python :: 3.10
Classifier: Programming Language :: Python :: 3.11
Classifier: Programming Language :: Python :: 3.12
Classifier: Programming Language :: Python :: 3.13
Classifier: Operating System :: OS Independent
Requires-Python: >=3.10
License-File: LICENSE
Requires-Dist: numpy>=1.20
Requires-Dist: pint>=0.24.1
Requires-Dist: pyyaml
Requires-Dist: uncertainties
Requires-Dist: striprtf
Requires-Dist: tzlocal
Requires-Dist: packaging
Requires-Dist: python-dateutil
Requires-Dist: openpyxl>=3.0.0
Requires-Dist: olefile>=0.47
Requires-Dist: h5netcdf>=1.0
Requires-Dist: pandas>=2.0
Requires-Dist: babel>=2.15
Requires-Dist: xarray>=2024.10.0
Requires-Dist: dgbowl-schemas>=123
Provides-Extra: testing
Requires-Dist: pytest; extra == "testing"
Provides-Extra: docs
Requires-Dist: sphinx~=7.2; extra == "docs"
Requires-Dist: sphinx-rtd-theme~=1.3.0; extra == "docs"
Requires-Dist: autodoc-pydantic~=2.1.0; extra == "docs"
Dynamic: license-file
